synumses/__init__.py
synumses/one_dimension/__init__.py
synumses/one_dimension/functions.py
synumses/one_dimension/parameters.py
synumses/one_dimension/python_code_generator.py
synumses/one_dimension/python_code_generator_scharfetter_gummel_bernoulli.py
synumses/one_dimension/scharfetter_gummel_bernoulli.py
synumses/one_dimension/scharfetter_gummel_bernoulli_new.py
synumses/one_dimension/scharfetter_gummel_bernoulli_ok.py
synumses/one_dimension/scharfetter_gummel_bernoulli_p4_no_simplify.py
synumses/one_dimension/scharfetter_gummel_bernoulli_p4_simplify.py
synumses/one_dimension/scharfetter_gummel_bernoulli_p6_mean_simplify.py
synumses/one_dimension/scharfetter_gummel_bernoulli_p6_no_simplify.py
synumses/one_dimension/scharfetter_gummel_bernoulli_p6_simplify.py
synumses/one_dimension/scharfetter_gummel_bernoulli_simpify.py
synumses/one_dimension/scharfetter_gummel_bernoulli_without_simplify.py
synumses/one_dimension/solver.py
synumses_pkg_pabele-0.8.4.dist-info/METADATA
synumses_pkg_pabele-0.8.4.dist-info/WHEEL
synumses_pkg_pabele-0.8.4.dist-info/top_level.txt
synumses_pkg_pabele-0.8.4.dist-info/RECORD
